{
  "applications": [
    {
      "id": "tempsoft",
      "name": "Tempsoft",
      "version": "0.9.7",
      "vendor": "ADP",
      "description": "Decentralized zero tolerance hardware",
      "categoryId": "inventory",
      "applicationSize": "Small",
      "status": "Standard",
      "condition": [
        { "label": "fy20q1", "value": "Good" },
        { "label": "fy20q2", "value": "Average" },
        { "label": "fy20q3", "value": "Good" }
      ],
      "months_to_renew_support": 1,
      "hostedtype": "OnPremise1",
      "support_cost": "478",
      "type": "InHouseDev",
      "deployment_date": "8/12/12",
      "licensing_cost": "28",
      "end_of_life": "4/6/19",
      "rating": "good",
      "investment_24m": "950",
      "investment_number": 444,
      "sme_email": "Nikolia.Pundy@memento.net.au",
      "department": "Human Resources",
      "end_of_maintenance": "24/7/17",
      "integrations": [
        {
          "id": "int-117",
          "name": "INT-117",
          "version": "0.9.5",
          "description": "Praesent id massa id nisl venenatis lacinia. Aenean sit amet justo. Morbi ut odio.",
          "payload": "Purchase Order",
          "targetApplicationId": "hyperlocal",
          "categoryId": "email",
          "status": "Standard",
          "pattern": "Enrichment",
          "last_deployment_date": "2/3/17",
          "golive_date": "30/4/03",
          "decom_date": "18/4/12",
          "datacentre": "Asia Pacific (Melbourne)",
          "sme_name": "Roland Elijah",
          "complexity": "Medium",
          "department": "App Control",
          "logical_server": "CLOUD-A2A",
          "sme_email": "relijahe@memento.net.au"
        }
      ]
    }
  ]
}